spux/__init__.py
spux/__main__.py
spux/distributions/__init__.py
spux/distributions/distribution.py
spux/distributions/multivariate.py
spux/distributions/tensor.py
spux/drivers/__init__.py
spux/drivers/java.py
spux/executors/__init__.py
spux/executors/executor.py
spux/executors/serial.py
spux/executors/balancers/__init__.py
spux/executors/balancers/adaptive.py
spux/executors/balancers/balancer.py
spux/executors/mpi4py/__init__.py
spux/executors/mpi4py/ensemble.py
spux/executors/mpi4py/ensemble_contract.py
spux/executors/mpi4py/ensemble_resample.py
spux/executors/mpi4py/model.py
spux/executors/mpi4py/pool.py
spux/executors/mpi4py/pool_contract.py
spux/executors/mpi4py/connectors/__init__.py
spux/executors/mpi4py/connectors/legacy.py
spux/executors/mpi4py/connectors/spawn.py
spux/executors/mpi4py/connectors/split.py
spux/executors/mpi4py/connectors/utils.py
spux/executors/mpi4py/connectors/worker.py
spux/io/__init__.py
spux/io/checkpointer.py
spux/io/dumper.py
spux/io/formatter.py
spux/io/loader.py
spux/io/parameters.py
spux/io/report.py
spux/likelihoods/__init__.py
spux/likelihoods/direct.py
spux/likelihoods/ensemble.py
spux/likelihoods/likelihood.py
spux/likelihoods/pf.py
spux/likelihoods/replicates.py
spux/models/__init__.py
spux/models/ibm.py
spux/models/model.py
spux/models/randomwalk.py
spux/models/randomwalk_numba.py
spux/models/straightwalk.py
spux/plot/__init__.py
spux/plot/mpl.py
spux/plot/mpl_palette_colors.png
spux/plot/mpl_palette_pf.py
spux/plot/mpl_utils.py
spux/plot/profile.py
spux/processes/__init__.py
spux/processes/ornsteinuhlenbeck.py
spux/processes/precipitation.py
spux/processes/wastewater.py
spux/report/__init__.py
spux/report/generate.py
spux/report/templates/figure.tex
spux/report/templates/header.tex
spux/report/templates/miscellaneous.tex
spux/report/templates/performance.tex
spux/report/templates/report.tex
spux/report/templates/results.tex
spux/report/templates/setup.tex
spux/report/templates/spux-logo.png
spux/report/templates/table.tex
spux-0.4.0.dist-info/LICENSE
spux-0.4.0.dist-info/METADATA
spux-0.4.0.dist-info/NOTICE
spux-0.4.0.dist-info/WHEEL
spux-0.4.0.dist-info/top_level.txt
spux-0.4.0.dist-info/RECORD
