Metadata-Version: 2.1
Name: spux
Version: 0.4.0
Summary: SPUX: Scalable Package for Uncertainty Quantification
Home-page: https://gitlab.com/siam-sc/spux/
Author: Jonas Šukys, Marco Bacci, Uwe Schmitt, Mikołaj Rybiński
Author-email: jonas.sukys@eawag.ch, marco.bacci@eawag.ch, uwe.schmitt@id.ethz.ch, mikolaj.rybinski@id.ethz.ch
License: UNKNOWN
Keywords: Bayesian inference using hpc
Platform: UNKNOWN
Classifier: Development Status :: 5 - Production/Stable
Classifier: Intended Audience :: Science/Research
Classifier: License :: OSI Approved :: Apache Software License
Classifier: Natural Language :: English
Classifier: Topic :: Scientific/Engineering
Classifier: Programming Language :: Python :: 3
Classifier: Programming Language :: Python :: 3.7
Requires-Dist: numpy
Requires-Dist: sympy
Requires-Dist: mpi4py
Requires-Dist: pandas
Requires-Dist: setuptools
Requires-Dist: Cython
Requires-Dist: scipy
Requires-Dist: matplotlib
Requires-Dist: cloudpickle
Requires-Dist: pycallgraph
Requires-Dist: numba
Requires-Dist: gprof2dot
Requires-Dist: suftware
Requires-Dist: pygit2
Requires-Dist: reprozip
Requires-Dist: pylatex
